validate_it/__init__.py
validate_it/decorators.py
validate_it/errors.py
validate_it/options.py
validate_it/options.pyi
validate_it/utils.py
validate_it-0.11.2.dist-info/LICENSE.txt
validate_it-0.11.2.dist-info/WHEEL
validate_it-0.11.2.dist-info/METADATA
validate_it-0.11.2.dist-info/RECORD
