Metadata-Version: 2.1
Name: validate-it
Version: 0.11.2
Summary: Ultimate data validation tool built on top of the typing module
Home-page: https://github.com/ruslux/validate-it
License: MIT
Keywords: schema,validator,json,typing
Author: Ruslan Roskoshny
Author-email: i.am.yarger@gmail.com
Requires-Python: >=3.6,<4.0
Classifier: Development Status :: 4 - Beta
Classifier: License :: OSI Approved :: MIT License
Classifier: Operating System :: OS Independent
Classifier: Programming Language :: Python :: 3
Classifier: Programming Language :: Python :: 3.6
Classifier: Programming Language :: Python :: 3.7
Classifier: Programming Language :: Python :: 3.8
Classifier: Programming Language :: Python :: 3.9
Classifier: Programming Language :: Python :: Implementation :: PyPy
Project-URL: Repository, https://github.com/ruslux/validate-it
